shellchat/__init__.py
shellchat/__main__.py
shellchat/search_handler.py
ShellChat-0.6.0.dist-info/METADATA
ShellChat-0.6.0.dist-info/WHEEL
ShellChat-0.6.0.dist-info/entry_points.txt
ShellChat-0.6.0.dist-info/top_level.txt
ShellChat-0.6.0.dist-info/RECORD
