Metadata-Version: 2.1
Name: ShellChat
Version: 0.6.0
Summary: A simple chat client for the terminal
Author: Adriano R. de Sousa
Author-email: adrianorodriguesdsousa@ufpi.edu.br
License: MIT
Requires: click
Requires: flask
Requires: aiohttp
Requires: requests
Requires: rich
